flit_gettext/__init__.py
flit_gettext/_version.py
flit_gettext/core.py
flit_gettext/scm.py
flit_gettext/utils.py
flit_gettext-1.0.2.dist-info/licenses/LICENSE
flit_gettext-1.0.2.dist-info/WHEEL
flit_gettext-1.0.2.dist-info/METADATA
flit_gettext-1.0.2.dist-info/RECORD
