Metadata-Version: 2.4
Name: flit-gettext
Version: 1.0.2
Summary: Compiling gettext i18n messages during project bundling.
Keywords: flit,pep518,build,packaging,gettext
Author-email: Johannes Maron <johannes@maron.family>
Requires-Python: >=3.10
Classifier: Development Status :: 5 - Production/Stable
Classifier: Programming Language :: Python
Classifier: Environment :: Web Environment
Classifier: License :: OSI Approved :: BSD License
Classifier: Intended Audience :: Developers
Classifier: Operating System :: OS Independent
Classifier: Topic :: Software Development
Classifier: Topic :: Software Development :: Libraries :: Python Modules
Classifier: Programming Language :: Python
Classifier: Programming Language :: Python :: 3
Classifier: Programming Language :: Python :: 3 :: Only
Classifier: Programming Language :: Python :: 3.10
Classifier: Programming Language :: Python :: 3.11
Classifier: Programming Language :: Python :: 3.12
Classifier: Programming Language :: Python :: 3.13
Classifier: Programming Language :: Python :: 3.14
License-File: LICENSE
Requires-Dist: flit-core~=3.5
Requires-Dist: flit-scm ; extra == "scm"
Requires-Dist: pytest ; extra == "test"
Requires-Dist: pytest-cov ; extra == "test"
Requires-Dist: flit-scm ; extra == "test"
Requires-Dist: build ; extra == "test"
Requires-Dist: wheel ; extra == "test"
Project-URL: Changelog, https://github.com/codingjoe/flit-gettext/releases
Project-URL: Project-URL, https://github.com/codingjoe/flit-gettext
Provides-Extra: scm
Provides-Extra: test
